{
  "textures": {
    "layer0": "anime_magic:item/diamond_sword_7006"
  },
  "elements": [
    {
      "from": [
        7,
        0,
        7
      ],
      "to": [
        9,
        2,
        9
      ],
      "faces": {
        "north": {
          "uv": [
            56.0,
            0.0,
            72.0,
            16.0
          ],
          "texture": "#layer0"
        },
        "east": {
          "uv": [
            56.0,
            0.0,
            72.0,
            16.0
          ],
          "texture": "#layer0"
        },
        "south": {
          "uv": [
            56.0,
            0.0,
            72.0,
            16.0
          ],
          "texture": "#layer0"
        },
        "west": {
          "uv": [
            56.0,
            0.0,
            72.0,
            16.0
          ],
          "texture": "#layer0"
        },
        "up": {
          "uv": [
            56.0,
            56.0,
            72.0,
            72.0
          ],
          "texture": "#layer0"
        },
        "down": {
          "uv": [
            56.0,
            56.0,
            72.0,
            72.0
          ],
          "texture": "#layer0"
        }
      }
    },
    {
      "from": [
        6.5,
        1,
        6.5
      ],
      "to": [
        9.5,
        3,
        9.5
      ],
      "faces": {
        "north": {
          "uv": [
            52.0,
            8.0,
            76.0,
            24.0
          ],
          "texture": "#layer0"
        },
        "east": {
          "uv": [
            52.0,
            8.0,
            76.0,
            24.0
          ],
          "texture": "#layer0"
        },
        "south": {
          "uv": [
            52.0,
            8.0,
            76.0,
            24.0
          ],
          "texture": "#layer0"
        },
        "west": {
          "uv": [
            52.0,
            8.0,
            76.0,
            24.0
          ],
          "texture": "#layer0"
        },
        "up": {
          "uv": [
            52.0,
            52.0,
            76.0,
            76.0
          ],
          "texture": "#layer0"
        },
        "down": {
          "uv": [
            52.0,
            52.0,
            76.0,
            76.0
          ],
          "texture": "#layer0"
        }
      }
    },
    {
      "from": [
        7,
        2,
        6.5
      ],
      "to": [
        9,
        4,
        9.5
      ],
      "faces": {
        "north": {
          "uv": [
            56.0,
            16.0,
            72.0,
            32.0
          ],
          "texture": "#layer0"
        },
        "east": {
          "uv": [
            52.0,
            16.0,
            76.0,
            32.0
          ],
          "texture": "#layer0"
        },
        "south": {
          "uv": [
            56.0,
            16.0,
            72.0,
            32.0
          ],
          "texture": "#layer0"
        },
        "west": {
          "uv": [
            52.0,
            16.0,
            76.0,
            32.0
          ],
          "texture": "#layer0"
        },
        "up": {
          "uv": [
            56.0,
            52.0,
            72.0,
            76.0
          ],
          "texture": "#layer0"
        },
        "down": {
          "uv": [
            56.0,
            52.0,
            72.0,
            76.0
          ],
          "texture": "#layer0"
        }
      }
    },
    {
      "from": [
        7,
        4,
        6.5
      ],
      "to": [
        9,
        6,
        9.5
      ],
      "faces": {
        "north": {
          "uv": [
            56.0,
            32.0,
            72.0,
            48.0
          ],
          "texture": "#layer0"
        },
        "east": {
          "uv": [
            52.0,
            32.0,
            76.0,
            48.0
          ],
          "texture": "#layer0"
        },
        "south": {
          "uv": [
            56.0,
            32.0,
            72.0,
            48.0
          ],
          "texture": "#layer0"
        },
        "west": {
          "uv": [
            52.0,
            32.0,
            76.0,
            48.0
          ],
          "texture": "#layer0"
        },
        "up": {
          "uv": [
            56.0,
            52.0,
            72.0,
            76.0
          ],
          "texture": "#layer0"
        },
        "down": {
          "uv": [
            56.0,
            52.0,
            72.0,
            76.0
          ],
          "texture": "#layer0"
        }
      }
    },
    {
      "from": [
        7,
        6,
        6.5
      ],
      "to": [
        9,
        8,
        9.5
      ],
      "faces": {
        "north": {
          "uv": [
            56.0,
            48.0,
            72.0,
            64.0
          ],
          "texture": "#layer0"
        },
        "east": {
          "uv": [
            52.0,
            48.0,
            76.0,
            64.0
          ],
          "texture": "#layer0"
        },
        "south": {
          "uv": [
            56.0,
            48.0,
            72.0,
            64.0
          ],
          "texture": "#layer0"
        },
        "west": {
          "uv": [
            52.0,
            48.0,
            76.0,
            64.0
          ],
          "texture": "#layer0"
        },
        "up": {
          "uv": [
            56.0,
            52.0,
            72.0,
            76.0
          ],
          "texture": "#layer0"
        },
        "down": {
          "uv": [
            56.0,
            52.0,
            72.0,
            76.0
          ],
          "texture": "#layer0"
        }
      }
    },
    {
      "from": [
        7,
        8,
        6.5
      ],
      "to": [
        9,
        10,
        9.5
      ],
      "faces": {
        "north": {
          "uv": [
            56.0,
            64.0,
            72.0,
            80.0
          ],
          "texture": "#layer0"
        },
        "east": {
          "uv": [
            52.0,
            64.0,
            76.0,
            80.0
          ],
          "texture": "#layer0"
        },
        "south": {
          "uv": [
            56.0,
            64.0,
            72.0,
            80.0
          ],
          "texture": "#layer0"
        },
        "west": {
          "uv": [
            52.0,
            64.0,
            76.0,
            80.0
          ],
          "texture": "#layer0"
        },
        "up": {
          "uv": [
            56.0,
            52.0,
            72.0,
            76.0
          ],
          "texture": "#layer0"
        },
        "down": {
          "uv": [
            56.0,
            52.0,
            72.0,
            76.0
          ],
          "texture": "#layer0"
        }
      }
    },
    {
      "from": [
        4,
        10,
        6.5
      ],
      "to": [
        12,
        11,
        9.5
      ],
      "faces": {
        "north": {
          "uv": [
            32.0,
            80.0,
            96.0,
            88.0
          ],
          "texture": "#layer0"
        },
        "east": {
          "uv": [
            52.0,
            80.0,
            76.0,
            88.0
          ],
          "texture": "#layer0"
        },
        "south": {
          "uv": [
            32.0,
            80.0,
            96.0,
            88.0
          ],
          "texture": "#layer0"
        },
        "west": {
          "uv": [
            52.0,
            80.0,
            76.0,
            88.0
          ],
          "texture": "#layer0"
        },
        "up": {
          "uv": [
            32.0,
            52.0,
            96.0,
            76.0
          ],
          "texture": "#layer0"
        },
        "down": {
          "uv": [
            32.0,
            52.0,
            96.0,
            76.0
          ],
          "texture": "#layer0"
        }
      }
    },
    {
      "from": [
        5,
        11,
        7
      ],
      "to": [
        11,
        12,
        9
      ],
      "faces": {
        "north": {
          "uv": [
            40.0,
            88.0,
            88.0,
            96.0
          ],
          "texture": "#layer0"
        },
        "east": {
          "uv": [
            56.0,
            88.0,
            72.0,
            96.0
          ],
          "texture": "#layer0"
        },
        "south": {
          "uv": [
            40.0,
            88.0,
            88.0,
            96.0
          ],
          "texture": "#layer0"
        },
        "west": {
          "uv": [
            56.0,
            88.0,
            72.0,
            96.0
          ],
          "texture": "#layer0"
        },
        "up": {
          "uv": [
            40.0,
            56.0,
            88.0,
            72.0
          ],
          "texture": "#layer0"
        },
        "down": {
          "uv": [
            40.0,
            56.0,
            88.0,
            72.0
          ],
          "texture": "#layer0"
        }
      }
    },
    {
      "from": [
        6.5,
        12,
        7
      ],
      "to": [
        9.5,
        15,
        9
      ],
      "faces": {
        "north": {
          "uv": [
            52.0,
            96.0,
            76.0,
            120.0
          ],
          "texture": "#layer0"
        },
        "east": {
          "uv": [
            56.0,
            96.0,
            72.0,
            120.0
          ],
          "texture": "#layer0"
        },
        "south": {
          "uv": [
            52.0,
            96.0,
            76.0,
            120.0
          ],
          "texture": "#layer0"
        },
        "west": {
          "uv": [
            56.0,
            96.0,
            72.0,
            120.0
          ],
          "texture": "#layer0"
        },
        "up": {
          "uv": [
            52.0,
            56.0,
            76.0,
            72.0
          ],
          "texture": "#layer0"
        },
        "down": {
          "uv": [
            52.0,
            56.0,
            76.0,
            72.0
          ],
          "texture": "#layer0"
        }
      }
    },
    {
      "from": [
        6.8,
        15,
        7
      ],
      "to": [
        9.2,
        18,
        9
      ],
      "faces": {
        "north": {
          "uv": [
            54.4,
            120.0,
            73.6,
            144.0
          ],
          "texture": "#layer0"
        },
        "east": {
          "uv": [
            56.0,
            120.0,
            72.0,
            144.0
          ],
          "texture": "#layer0"
        },
        "south": {
          "uv": [
            54.4,
            120.0,
            73.6,
            144.0
          ],
          "texture": "#layer0"
        },
        "west": {
          "uv": [
            56.0,
            120.0,
            72.0,
            144.0
          ],
          "texture": "#layer0"
        },
        "up": {
          "uv": [
            54.4,
            56.0,
            73.6,
            72.0
          ],
          "texture": "#layer0"
        },
        "down": {
          "uv": [
            54.4,
            56.0,
            73.6,
            72.0
          ],
          "texture": "#layer0"
        }
      }
    },
    {
      "from": [
        7.1,
        18,
        7
      ],
      "to": [
        8.9,
        21,
        9
      ],
      "faces": {
        "north": {
          "uv": [
            56.8,
            144.0,
            71.2,
            168.0
          ],
          "texture": "#layer0"
        },
        "east": {
          "uv": [
            56.0,
            144.0,
            72.0,
            168.0
          ],
          "texture": "#layer0"
        },
        "south": {
          "uv": [
            56.8,
            144.0,
            71.2,
            168.0
          ],
          "texture": "#layer0"
        },
        "west": {
          "uv": [
            56.0,
            144.0,
            72.0,
            168.0
          ],
          "texture": "#layer0"
        },
        "up": {
          "uv": [
            56.8,
            56.0,
            71.2,
            72.0
          ],
          "texture": "#layer0"
        },
        "down": {
          "uv": [
            56.8,
            56.0,
            71.2,
            72.0
          ],
          "texture": "#layer0"
        }
      }
    },
    {
      "from": [
        7.3,
        21,
        7
      ],
      "to": [
        8.7,
        24,
        9
      ],
      "faces": {
        "north": {
          "uv": [
            58.4,
            168.0,
            69.6,
            192.0
          ],
          "texture": "#layer0"
        },
        "east": {
          "uv": [
            56.0,
            168.0,
            72.0,
            192.0
          ],
          "texture": "#layer0"
        },
        "south": {
          "uv": [
            58.4,
            168.0,
            69.6,
            192.0
          ],
          "texture": "#layer0"
        },
        "west": {
          "uv": [
            56.0,
            168.0,
            72.0,
            192.0
          ],
          "texture": "#layer0"
        },
        "up": {
          "uv": [
            58.4,
            56.0,
            69.6,
            72.0
          ],
          "texture": "#layer0"
        },
        "down": {
          "uv": [
            58.4,
            56.0,
            69.6,
            72.0
          ],
          "texture": "#layer0"
        }
      }
    },
    {
      "from": [
        7.5,
        24,
        7
      ],
      "to": [
        8.5,
        27,
        9
      ],
      "faces": {
        "north": {
          "uv": [
            60.0,
            192.0,
            68.0,
            216.0
          ],
          "texture": "#layer0"
        },
        "east": {
          "uv": [
            56.0,
            192.0,
            72.0,
            216.0
          ],
          "texture": "#layer0"
        },
        "south": {
          "uv": [
            60.0,
            192.0,
            68.0,
            216.0
          ],
          "texture": "#layer0"
        },
        "west": {
          "uv": [
            56.0,
            192.0,
            72.0,
            216.0
          ],
          "texture": "#layer0"
        },
        "up": {
          "uv": [
            60.0,
            56.0,
            68.0,
            72.0
          ],
          "texture": "#layer0"
        },
        "down": {
          "uv": [
            60.0,
            56.0,
            68.0,
            72.0
          ],
          "texture": "#layer0"
        }
      }
    },
    {
      "from": [
        6,
        13,
        8
      ],
      "to": [
        6.5,
        17,
        8
      ],
      "faces": {
        "north": {
          "uv": [
            48.0,
            104.0,
            52.0,
            136.0
          ],
          "texture": "#layer0"
        },
        "east": {
          "uv": [
            64.0,
            104.0,
            64.0,
            136.0
          ],
          "texture": "#layer0"
        },
        "south": {
          "uv": [
            48.0,
            104.0,
            52.0,
            136.0
          ],
          "texture": "#layer0"
        },
        "west": {
          "uv": [
            64.0,
            104.0,
            64.0,
            136.0
          ],
          "texture": "#layer0"
        },
        "up": {
          "uv": [
            48.0,
            64.0,
            52.0,
            64.0
          ],
          "texture": "#layer0"
        },
        "down": {
          "uv": [
            48.0,
            64.0,
            52.0,
            64.0
          ],
          "texture": "#layer0"
        }
      }
    },
    {
      "from": [
        9.5,
        13,
        8
      ],
      "to": [
        10,
        17,
        8
      ],
      "faces": {
        "north": {
          "uv": [
            76.0,
            104.0,
            80.0,
            136.0
          ],
          "texture": "#layer0"
        },
        "east": {
          "uv": [
            64.0,
            104.0,
            64.0,
            136.0
          ],
          "texture": "#layer0"
        },
        "south": {
          "uv": [
            76.0,
            104.0,
            80.0,
            136.0
          ],
          "texture": "#layer0"
        },
        "west": {
          "uv": [
            64.0,
            104.0,
            64.0,
            136.0
          ],
          "texture": "#layer0"
        },
        "up": {
          "uv": [
            76.0,
            64.0,
            80.0,
            64.0
          ],
          "texture": "#layer0"
        },
        "down": {
          "uv": [
            76.0,
            64.0,
            80.0,
            64.0
          ],
          "texture": "#layer0"
        }
      }
    },
    {
      "from": [
        6,
        18,
        8
      ],
      "to": [
        6.3,
        22,
        8
      ],
      "faces": {
        "north": {
          "uv": [
            48.0,
            144.0,
            50.4,
            176.0
          ],
          "texture": "#layer0"
        },
        "east": {
          "uv": [
            64.0,
            144.0,
            64.0,
            176.0
          ],
          "texture": "#layer0"
        },
        "south": {
          "uv": [
            48.0,
            144.0,
            50.4,
            176.0
          ],
          "texture": "#layer0"
        },
        "west": {
          "uv": [
            64.0,
            144.0,
            64.0,
            176.0
          ],
          "texture": "#layer0"
        },
        "up": {
          "uv": [
            48.0,
            64.0,
            50.4,
            64.0
          ],
          "texture": "#layer0"
        },
        "down": {
          "uv": [
            48.0,
            64.0,
            50.4,
            64.0
          ],
          "texture": "#layer0"
        }
      }
    },
    {
      "from": [
        9.7,
        18,
        8
      ],
      "to": [
        10,
        22,
        8
      ],
      "faces": {
        "north": {
          "uv": [
            77.6,
            144.0,
            80.0,
            176.0
          ],
          "texture": "#layer0"
        },
        "east": {
          "uv": [
            64.0,
            144.0,
            64.0,
            176.0
          ],
          "texture": "#layer0"
        },
        "south": {
          "uv": [
            77.6,
            144.0,
            80.0,
            176.0
          ],
          "texture": "#layer0"
        },
        "west": {
          "uv": [
            64.0,
            144.0,
            64.0,
            176.0
          ],
          "texture": "#layer0"
        },
        "up": {
          "uv": [
            77.6,
            64.0,
            80.0,
            64.0
          ],
          "texture": "#layer0"
        },
        "down": {
          "uv": [
            77.6,
            64.0,
            80.0,
            64.0
          ],
          "texture": "#layer0"
        }
      }
    },
    {
      "from": [
        7.6,
        26,
        7.4
      ],
      "to": [
        8.4,
        29,
        8.6
      ],
      "faces": {
        "north": {
          "uv": [
            60.8,
            208.0,
            67.2,
            232.0
          ],
          "texture": "#layer0"
        },
        "east": {
          "uv": [
            59.2,
            208.0,
            68.8,
            232.0
          ],
          "texture": "#layer0"
        },
        "south": {
          "uv": [
            60.8,
            208.0,
            67.2,
            232.0
          ],
          "texture": "#layer0"
        },
        "west": {
          "uv": [
            59.2,
            208.0,
            68.8,
            232.0
          ],
          "texture": "#layer0"
        },
        "up": {
          "uv": [
            60.8,
            59.2,
            67.2,
            68.8
          ],
          "texture": "#layer0"
        },
        "down": {
          "uv": [
            60.8,
            59.2,
            67.2,
            68.8
          ],
          "texture": "#layer0"
        }
      }
    },
    {
      "from": [
        7.8,
        28,
        7.6
      ],
      "to": [
        8.2,
        30,
        8.4
      ],
      "faces": {
        "north": {
          "uv": [
            62.4,
            224.0,
            65.6,
            240.0
          ],
          "texture": "#layer0"
        },
        "east": {
          "uv": [
            60.8,
            224.0,
            67.2,
            240.0
          ],
          "texture": "#layer0"
        },
        "south": {
          "uv": [
            62.4,
            224.0,
            65.6,
            240.0
          ],
          "texture": "#layer0"
        },
        "west": {
          "uv": [
            60.8,
            224.0,
            67.2,
            240.0
          ],
          "texture": "#layer0"
        },
        "up": {
          "uv": [
            62.4,
            60.8,
            65.6,
            67.2
          ],
          "texture": "#layer0"
        },
        "down": {
          "uv": [
            62.4,
            60.8,
            65.6,
            67.2
          ],
          "texture": "#layer0"
        }
      }
    }
  ],
  "display": {
    "gui": {
      "rotation": [
        0,
        0,
        60
      ],
      "translation": [
        0,
        -3,
        0
      ],
      "scale": [
        0.35,
        0.35,
        0.35
      ]
    },
    "fixed": {
      "scale": [
        0.4,
        0.4,
        0.4
      ]
    }
  },
  "texture_size": [
    128,
    128
  ]
}
